XmlXL/__init__.py
XmlXL/converter.py
xltoxml-1.0.0.dist-info/METADATA
xltoxml-1.0.0.dist-info/WHEEL
xltoxml-1.0.0.dist-info/top_level.txt
xltoxml-1.0.0.dist-info/RECORD
