Metadata-Version: 2.2
Name: xltoxml
Version: 1.0.0
Summary: Convert Excel files to XML format
Requires-Dist: openpyxl
